MANIFEST.in
README.rst
requirements.txt
setup.py
tests/__init__.py
tests/test_main.py
tests/test_styles.py
tests/test_utils.py
tests/data/logo.png
tests/data/pathfinder_1.pdf
tests/data/pathfinder_1.xml
tests/data/pathfinder_v1.xsd
xml_archive_to_pdf/__init__.py
xml_archive_to_pdf/main.py
xml_archive_to_pdf/settings.py
xml_archive_to_pdf/styles.py
xml_archive_to_pdf/utils.py
xml_archive_to_pdf.egg-info/PKG-INFO
xml_archive_to_pdf.egg-info/SOURCES.txt
xml_archive_to_pdf.egg-info/dependency_links.txt
xml_archive_to_pdf.egg-info/entry_points.txt
xml_archive_to_pdf.egg-info/requires.txt
xml_archive_to_pdf.egg-info/top_level.txt