Metadata-Version: 1.1
Name: xml-archive-to-pdf
Version: 1.0.6
Summary: Transformation d'un fichier xml de type unistra:archive en fichier pdf
Home-page: https://github.com/unistra/xml-archive-to-pdf
Author: di-dip-unistra
Author-email: di-dip@unistra.fr
License: PSF
Download-URL: https://github.com/unistra/xml-archive-to-pdf
Platform: UNKNOWN
Classifier: Development Status :: 3 - Alpha
Classifier: Intended Audience :: Developers
Classifier: License :: OSI Approved :: BSD License
Classifier: Operating System :: OS Independent
Classifier: Programming Language :: Python :: 3.4
